djangocms_youtube/__init__.py
djangocms_youtube/cms_plugins.py
djangocms_youtube/compat.py
djangocms_youtube/conf.py
djangocms_youtube/exceptions.py
djangocms_youtube/forms.py
djangocms_youtube/models.py
djangocms_youtube/utils.py
djangocms_youtube/video_sitemap.py
djangocms_youtube/views.py
djangocms_youtube/widgets.py
djangocms_youtube/migrations/0001_initial.py
djangocms_youtube/migrations/__init__.py
djangocms_youtube/south_migrations/0001_initial.py
djangocms_youtube/south_migrations/__init__.py
djangocms_youtube/static/admin/css/djangocms_youtube/changeform.css
djangocms_youtube/static/admin/js/djangocms_youtube/changeform.js
djangocms_youtube/static/css/djangocms_youtube/djangocms_youtube.css
djangocms_youtube/static/js/djangocms_youtube/jquery.yt-player.js
djangocms_youtube/static/js/djangocms_youtube/greensock-js/TweenMax.js
djangocms_youtube/static/js/djangocms_youtube/greensock-js/TweenMax.min.js
djangocms_youtube/templates/djangocms_youtube/default.html
djangocms_youtube-0.2.1.dist-info/DESCRIPTION.rst
djangocms_youtube-0.2.1.dist-info/METADATA
djangocms_youtube-0.2.1.dist-info/RECORD
djangocms_youtube-0.2.1.dist-info/WHEEL
djangocms_youtube-0.2.1.dist-info/metadata.json
djangocms_youtube-0.2.1.dist-info/top_level.txt
