Metadata-Version: 2.0
Name: djangocms-youtube
Version: 0.2.1
Summary: YouTube embed plugin for your django-cms powered site with options for custom video thumbnails, analytics, SEO and more.
Home-page: https://github.com/mishbahr/djangocms-youtube
Author: Mishbah Razzaque
Author-email: mishbahx@gmail.com
License: BSD
Keywords: djangocms-youtube,YouTube,django-cms,cmsplugin-youtube
Platform: UNKNOWN
Classifier: Development Status :: 4 - Beta
Classifier: Framework :: Django
Classifier: Framework :: Django :: 1.6
Classifier: Framework :: Django :: 1.7
Classifier: Framework :: Django :: 1.8
Classifier: Intended Audience :: Developers
Classifier: License :: OSI Approved :: BSD License
Classifier: Natural Language :: English
Classifier: Programming Language :: Python :: 2.7
Classifier: Programming Language :: Python :: 3
Classifier: Programming Language :: Python :: 3.3
Requires-Dist: django-appconf
Requires-Dist: django-cms (>=3.0)
Requires-Dist: django-filer (>=0.9)
Requires-Dist: isodate (>=0.5.4)
Requires-Dist: jsonfield
Requires-Dist: requests
